{
  "id": "2222508",
  "name": "广东ZDR",
  "font_family": "iconfont",
  "css_prefix_text": "icon",
  "description": "",
  "glyphs": [
    {
      "icon_id": "20263164",
      "name": "布控",
      "font_class": "f_control-01",
      "unicode": "e975",
      "unicode_decimal": 59765
    },
    {
      "icon_id": "20263341",
      "name": "申请通过",
      "font_class": "f_adopt",
      "unicode": "e976",
      "unicode_decimal": 59766
    },
    {
      "icon_id": "20263385",
      "name": "全部审批",
      "font_class": "f_all",
      "unicode": "e977",
      "unicode_decimal": 59767
    },
    {
      "icon_id": "20263606",
      "name": "申请中",
      "font_class": "f_apply",
      "unicode": "e978",
      "unicode_decimal": 59768
    },
    {
      "icon_id": "20263643",
      "name": "待审批",
      "font_class": "f_approval",
      "unicode": "e979",
      "unicode_decimal": 59769
    },
    {
      "icon_id": "20263684",
      "name": "已反馈",
      "font_class": "f_complete",
      "unicode": "e97b",
      "unicode_decimal": 59771
    },
    {
      "icon_id": "20263867",
      "name": "联控",
      "font_class": "f_branch",
      "unicode": "e97c",
      "unicode_decimal": 59772
    },
    {
      "icon_id": "20263898",
      "name": "待反馈",
      "font_class": "f_feedback",
      "unicode": "e97d",
      "unicode_decimal": 59773
    },
    {
      "icon_id": "20263920",
      "name": "指令",
      "font_class": "f_piece",
      "unicode": "e97e",
      "unicode_decimal": 59774
    },
    {
      "icon_id": "20263950",
      "name": "退回",
      "font_class": "f_return",
      "unicode": "e97f",
      "unicode_decimal": 59775
    },
    {
      "icon_id": "20264014",
      "name": "轨迹",
      "font_class": "f_route",
      "unicode": "e980",
      "unicode_decimal": 59776
    },
    {
      "icon_id": "20264025",
      "name": "即将到期",
      "font_class": "f_time",
      "unicode": "e981",
      "unicode_decimal": 59777
    },
    {
      "icon_id": "20264040",
      "name": "待签收",
      "font_class": "f_wait",
      "unicode": "e982",
      "unicode_decimal": 59778
    },
    {
      "icon_id": "14095243",
      "name": "添加",
      "font_class": "l-add",
      "unicode": "e7b8",
      "unicode_decimal": 59320
    },
    {
      "icon_id": "7217328",
      "name": "编辑",
      "font_class": "l-bianji",
      "unicode": "e676",
      "unicode_decimal": 58998
    },
    {
      "icon_id": "18211589",
      "name": "禁用",
      "font_class": "l-jinyong",
      "unicode": "e7d5",
      "unicode_decimal": 59349
    },
    {
      "icon_id": "18289156",
      "name": "开始2",
      "font_class": "l-kaishi",
      "unicode": "e622",
      "unicode_decimal": 58914
    },
    {
      "icon_id": "19334609",
      "name": "待审批",
      "font_class": "l-Pendingapproval",
      "unicode": "e94d",
      "unicode_decimal": 59725
    },
    {
      "icon_id": "19334610",
      "name": "已审批",
      "font_class": "l-approved",
      "unicode": "e94e",
      "unicode_decimal": 59726
    },
    {
      "icon_id": "11842885",
      "name": "摘要",
      "font_class": "f-summary",
      "unicode": "e73a",
      "unicode_decimal": 59194
    },
    {
      "icon_id": "11842887",
      "name": "提示",
      "font_class": "f-error",
      "unicode": "e73b",
      "unicode_decimal": 59195
    },
    {
      "icon_id": "11843044",
      "name": "重置",
      "font_class": "l-reload",
      "unicode": "e715",
      "unicode_decimal": 59157
    },
    {
      "icon_id": "11843045",
      "name": "退出",
      "font_class": "l-poweroff",
      "unicode": "e716",
      "unicode_decimal": 59158
    },
    {
      "icon_id": "11843046",
      "name": "审批",
      "font_class": "l-review",
      "unicode": "e717",
      "unicode_decimal": 59159
    },
    {
      "icon_id": "11843047",
      "name": "搜索",
      "font_class": "l-search",
      "unicode": "e718",
      "unicode_decimal": 59160
    },
    {
      "icon_id": "11843048",
      "name": "向右",
      "font_class": "l-right",
      "unicode": "e719",
      "unicode_decimal": 59161
    },
    {
      "icon_id": "11843055",
      "name": "收起",
      "font_class": "l-up",
      "unicode": "e71a",
      "unicode_decimal": 59162
    },
    {
      "icon_id": "11843059",
      "name": "下拉",
      "font_class": "l-down",
      "unicode": "e71b",
      "unicode_decimal": 59163
    },
    {
      "icon_id": "11843071",
      "name": "向左",
      "font_class": "l-left",
      "unicode": "e71c",
      "unicode_decimal": 59164
    },
    {
      "icon_id": "11843060",
      "name": "取消",
      "font_class": "l-close",
      "unicode": "e71d",
      "unicode_decimal": 59165
    },
    {
      "icon_id": "11843065",
      "name": "确定",
      "font_class": "l-check",
      "unicode": "e71e",
      "unicode_decimal": 59166
    },
    {
      "icon_id": "11843051",
      "name": "置顶",
      "font_class": "l-topping",
      "unicode": "e71f",
      "unicode_decimal": 59167
    },
    {
      "icon_id": "11843068",
      "name": "下载",
      "font_class": "l-download",
      "unicode": "e720",
      "unicode_decimal": 59168
    },
    {
      "icon_id": "11843049",
      "name": "发布",
      "font_class": "l-send",
      "unicode": "e721",
      "unicode_decimal": 59169
    },
    {
      "icon_id": "11843050",
      "name": "换肤",
      "font_class": "l-skin",
      "unicode": "e722",
      "unicode_decimal": 59170
    },
    {
      "icon_id": "11843052",
      "name": "保存",
      "font_class": "l-save",
      "unicode": "e723",
      "unicode_decimal": 59171
    },
    {
      "icon_id": "11843054",
      "name": "设置",
      "font_class": "l-setting",
      "unicode": "e724",
      "unicode_decimal": 59172
    },
    {
      "icon_id": "11843056",
      "name": "人员",
      "font_class": "l-user",
      "unicode": "e726",
      "unicode_decimal": 59174
    },
    {
      "icon_id": "11843062",
      "name": "删除",
      "font_class": "l-delete",
      "unicode": "e727",
      "unicode_decimal": 59175
    },
    {
      "icon_id": "11843064",
      "name": "消息",
      "font_class": "l-bell",
      "unicode": "e729",
      "unicode_decimal": 59177
    },
    {
      "icon_id": "11843069",
      "name": "链接",
      "font_class": "l-link",
      "unicode": "e72a",
      "unicode_decimal": 59178
    },
    {
      "icon_id": "11843070",
      "name": "定位",
      "font_class": "l-location",
      "unicode": "e73c",
      "unicode_decimal": 59196
    },
    {
      "icon_id": "11843053",
      "name": "摘要",
      "font_class": "l-summary",
      "unicode": "e73d",
      "unicode_decimal": 59197
    },
    {
      "icon_id": "11843072",
      "name": "列表",
      "font_class": "l-list",
      "unicode": "e73e",
      "unicode_decimal": 59198
    },
    {
      "icon_id": "11843057",
      "name": "新增文件",
      "font_class": "l-add-file",
      "unicode": "e73f",
      "unicode_decimal": 59199
    },
    {
      "icon_id": "11843058",
      "name": "word",
      "font_class": "l-word",
      "unicode": "e740",
      "unicode_decimal": 59200
    },
    {
      "icon_id": "11843063",
      "name": "添加文件",
      "font_class": "l-addfolder",
      "unicode": "e741",
      "unicode_decimal": 59201
    },
    {
      "icon_id": "11843066",
      "name": "excel",
      "font_class": "l-excel",
      "unicode": "e742",
      "unicode_decimal": 59202
    },
    {
      "icon_id": "11843067",
      "name": "日期",
      "font_class": "l-calendar",
      "unicode": "e743",
      "unicode_decimal": 59203
    },
    {
      "icon_id": "11843061",
      "name": "编辑",
      "font_class": "l-edit",
      "unicode": "e744",
      "unicode_decimal": 59204
    },
    {
      "icon_id": "11855920",
      "name": "导入",
      "font_class": "l-import",
      "unicode": "e745",
      "unicode_decimal": 59205
    },
    {
      "icon_id": "11855921",
      "name": "导出",
      "font_class": "l-export",
      "unicode": "e746",
      "unicode_decimal": 59206
    },
    {
      "icon_id": "11875117",
      "name": "批次号",
      "font_class": "l-file",
      "unicode": "e747",
      "unicode_decimal": 59207
    },
    {
      "icon_id": "11999191",
      "name": "相机",
      "font_class": "l-camera",
      "unicode": "e748",
      "unicode_decimal": 59208
    },
    {
      "icon_id": "12181734",
      "name": "照片",
      "font_class": "l-photo",
      "unicode": "e749",
      "unicode_decimal": 59209
    },
    {
      "icon_id": "12181986",
      "name": "照片",
      "font_class": "f-photo",
      "unicode": "e74a",
      "unicode_decimal": 59210
    },
    {
      "icon_id": "12182045",
      "name": "ie浏览器",
      "font_class": "f-ie",
      "unicode": "e74b",
      "unicode_decimal": 59211
    },
    {
      "icon_id": "12182046",
      "name": "车辆",
      "font_class": "f-car",
      "unicode": "e74c",
      "unicode_decimal": 59212
    },
    {
      "icon_id": "12182047",
      "name": "维护",
      "font_class": "f-maintain",
      "unicode": "e74d",
      "unicode_decimal": 59213
    },
    {
      "icon_id": "12182048",
      "name": "控制",
      "font_class": "f-control",
      "unicode": "e74e",
      "unicode_decimal": 59214
    },
    {
      "icon_id": "12182049",
      "name": "监控",
      "font_class": "f-monitor",
      "unicode": "e74f",
      "unicode_decimal": 59215
    },
    {
      "icon_id": "12182050",
      "name": "预警",
      "font_class": "f-Earlywarning",
      "unicode": "e750",
      "unicode_decimal": 59216
    },
    {
      "icon_id": "12182439",
      "name": "设置",
      "font_class": "f-setting",
      "unicode": "e751",
      "unicode_decimal": 59217
    },
    {
      "icon_id": "12182440",
      "name": "统计",
      "font_class": "f-statistics",
      "unicode": "e752",
      "unicode_decimal": 59218
    },
    {
      "icon_id": "12182441",
      "name": "语音",
      "font_class": "f-voice",
      "unicode": "e753",
      "unicode_decimal": 59219
    },
    {
      "icon_id": "12182442",
      "name": "发送",
      "font_class": "f-send",
      "unicode": "e754",
      "unicode_decimal": 59220
    },
    {
      "icon_id": "12183420",
      "name": "审批",
      "font_class": "f-Approval",
      "unicode": "e755",
      "unicode_decimal": 59221
    },
    {
      "icon_id": "12184999",
      "name": "时间",
      "font_class": "f-timel",
      "unicode": "e756",
      "unicode_decimal": 59222
    },
    {
      "icon_id": "12185000",
      "name": "处置中心",
      "font_class": "f-Disposalcenter",
      "unicode": "e757",
      "unicode_decimal": 59223
    },
    {
      "icon_id": "12240121",
      "name": "更多",
      "font_class": "f-more-gengduo",
      "unicode": "e758",
      "unicode_decimal": 59224
    },
    {
      "icon_id": "12240122",
      "name": "已审批",
      "font_class": "f-Approved-yishenpi",
      "unicode": "e759",
      "unicode_decimal": 59225
    },
    {
      "icon_id": "12240123",
      "name": "未审批",
      "font_class": "f-Notexamined-weishenpi",
      "unicode": "e75a",
      "unicode_decimal": 59226
    },
    {
      "icon_id": "12269698",
      "name": "重点",
      "font_class": "f-focus",
      "unicode": "e75b",
      "unicode_decimal": 59227
    },
    {
      "icon_id": "12269699",
      "name": "l-Focus-重点",
      "font_class": "l-focus",
      "unicode": "e75c",
      "unicode_decimal": 59228
    },
    {
      "icon_id": "12270947",
      "name": "吸毒",
      "font_class": "f-drug",
      "unicode": "e75d",
      "unicode_decimal": 59229
    },
    {
      "icon_id": "12270948",
      "name": "前科",
      "font_class": "f-previous",
      "unicode": "e75e",
      "unicode_decimal": 59230
    },
    {
      "icon_id": "12270949",
      "name": "逃跑",
      "font_class": "f-run",
      "unicode": "e75f",
      "unicode_decimal": 59231
    },
    {
      "icon_id": "12439669",
      "name": "精神病",
      "font_class": "f-Mentalillness",
      "unicode": "e760",
      "unicode_decimal": 59232
    },
    {
      "icon_id": "12439673",
      "name": "涉毒",
      "font_class": "f-poison",
      "unicode": "e761",
      "unicode_decimal": 59233
    },
    {
      "icon_id": "12439675",
      "name": "涉恐人员",
      "font_class": "f-Fear",
      "unicode": "e762",
      "unicode_decimal": 59234
    },
    {
      "icon_id": "12439670",
      "name": "刑事犯罪",
      "font_class": "f-lcriminal",
      "unicode": "e763",
      "unicode_decimal": 59235
    },
    {
      "icon_id": "12439671",
      "name": "安保",
      "font_class": "f-security",
      "unicode": "e764",
      "unicode_decimal": 59236
    },
    {
      "icon_id": "12439672",
      "name": "重点人员",
      "font_class": "f-Keypersonnel",
      "unicode": "e765",
      "unicode_decimal": 59237
    },
    {
      "icon_id": "12439674",
      "name": "涉稳",
      "font_class": "f-Stable",
      "unicode": "e766",
      "unicode_decimal": 59238
    },
    {
      "icon_id": "12439668",
      "name": "信",
      "font_class": "f-letterr",
      "unicode": "e767",
      "unicode_decimal": 59239
    },
    {
      "icon_id": "12451268",
      "name": "帮助",
      "font_class": "l-help",
      "unicode": "e768",
      "unicode_decimal": 59240
    },
    {
      "icon_id": "12595319",
      "name": "身份证",
      "font_class": "l-idcard",
      "unicode": "e769",
      "unicode_decimal": 59241
    },
    {
      "icon_id": "12595318",
      "name": "身份证",
      "font_class": "f-idcard",
      "unicode": "e76a",
      "unicode_decimal": 59242
    },
    {
      "icon_id": "12828014",
      "name": "通知",
      "font_class": "f-notice",
      "unicode": "e76b",
      "unicode_decimal": 59243
    },
    {
      "icon_id": "12828015",
      "name": "工作台",
      "font_class": "f-Workbench",
      "unicode": "e76c",
      "unicode_decimal": 59244
    },
    {
      "icon_id": "12828016",
      "name": "合成作战",
      "font_class": "f-syntheticcombat",
      "unicode": "e76d",
      "unicode_decimal": 59245
    },
    {
      "icon_id": "12828017",
      "name": "刊物",
      "font_class": "f-journal",
      "unicode": "e76e",
      "unicode_decimal": 59246
    },
    {
      "icon_id": "12828018",
      "name": "旗帜",
      "font_class": "f-flag",
      "unicode": "e76f",
      "unicode_decimal": 59247
    },
    {
      "icon_id": "12828019",
      "name": "统一指令logo",
      "font_class": "l-tongyizhilinglogo",
      "unicode": "e770",
      "unicode_decimal": 59248
    },
    {
      "icon_id": "12882850",
      "name": "最左",
      "font_class": "l-mostleft",
      "unicode": "e771",
      "unicode_decimal": 59249
    },
    {
      "icon_id": "12882852",
      "name": "最右",
      "font_class": "l-mostfight",
      "unicode": "e772",
      "unicode_decimal": 59250
    },
    {
      "icon_id": "12882853",
      "name": "双重右",
      "font_class": "l-doublefight",
      "unicode": "e773",
      "unicode_decimal": 59251
    },
    {
      "icon_id": "12882855",
      "name": "双重左",
      "font_class": "l-doubleleft",
      "unicode": "e774",
      "unicode_decimal": 59252
    },
    {
      "icon_id": "12882880",
      "name": "加",
      "font_class": "l-plus",
      "unicode": "e775",
      "unicode_decimal": 59253
    },
    {
      "icon_id": "12882881",
      "name": "减",
      "font_class": "l-minus",
      "unicode": "e776",
      "unicode_decimal": 59254
    },
    {
      "icon_id": "13570006",
      "name": "左对齐",
      "font_class": "l-alignleft",
      "unicode": "e777",
      "unicode_decimal": 59255
    },
    {
      "icon_id": "13570007",
      "name": "菜单",
      "font_class": "l-menu",
      "unicode": "e778",
      "unicode_decimal": 59256
    },
    {
      "icon_id": "13570008",
      "name": "无序列表",
      "font_class": "l-unorderedlist",
      "unicode": "e779",
      "unicode_decimal": 59257
    },
    {
      "icon_id": "13570009",
      "name": "右对齐",
      "font_class": "l-alignright",
      "unicode": "e77a",
      "unicode_decimal": 59258
    },
    {
      "icon_id": "13570010",
      "name": "中间对齐",
      "font_class": "l-aligncenter",
      "unicode": "e77b",
      "unicode_decimal": 59259
    },
    {
      "icon_id": "13672685",
      "name": "线索管理",
      "font_class": "f-clue",
      "unicode": "e77c",
      "unicode_decimal": 59260
    },
    {
      "icon_id": "13672820",
      "name": "信息收件",
      "font_class": "f-inReceiving",
      "unicode": "e77e",
      "unicode_decimal": 59262
    },
    {
      "icon_id": "13672821",
      "name": "指令发件",
      "font_class": "f-inOutgoing",
      "unicode": "e77f",
      "unicode_decimal": 59263
    },
    {
      "icon_id": "13672822",
      "name": "信息上报",
      "font_class": "f-Report",
      "unicode": "e780",
      "unicode_decimal": 59264
    },
    {
      "icon_id": "13672823",
      "name": "指令收件",
      "font_class": "f-insReceiving",
      "unicode": "e781",
      "unicode_decimal": 59265
    },
    {
      "icon_id": "13672824",
      "name": "信息新增",
      "font_class": "f-inadd",
      "unicode": "e782",
      "unicode_decimal": 59266
    },
    {
      "icon_id": "13672926",
      "name": "通知通报",
      "font_class": "f-Notice-",
      "unicode": "e783",
      "unicode_decimal": 59267
    },
    {
      "icon_id": "13672927",
      "name": "通知通报发件",
      "font_class": "f-Noticesend",
      "unicode": "e784",
      "unicode_decimal": 59268
    },
    {
      "icon_id": "13672928",
      "name": "通知通报收件",
      "font_class": "f-NoReceiving",
      "unicode": "e785",
      "unicode_decimal": 59269
    },
    {
      "icon_id": "13672967",
      "name": "点赞",
      "font_class": "l-like",
      "unicode": "e786",
      "unicode_decimal": 59270
    },
    {
      "icon_id": "13672968",
      "name": "点赞",
      "font_class": "f-like",
      "unicode": "e787",
      "unicode_decimal": 59271
    },
    {
      "icon_id": "13672969",
      "name": "踩",
      "font_class": "f-Stepon",
      "unicode": "e788",
      "unicode_decimal": 59272
    },
    {
      "icon_id": "13672970",
      "name": "踩",
      "font_class": "l-Stepon",
      "unicode": "e789",
      "unicode_decimal": 59273
    },
    {
      "icon_id": "13673010",
      "name": "合作",
      "font_class": "f-Cooperation",
      "unicode": "e78a",
      "unicode_decimal": 59274
    },
    {
      "icon_id": "13673608",
      "name": "疫情专项",
      "font_class": "f-epidemic",
      "unicode": "e78b",
      "unicode_decimal": 59275
    },
    {
      "icon_id": "13834324",
      "name": "公司",
      "font_class": "f-company",
      "unicode": "e78c",
      "unicode_decimal": 59276
    },
    {
      "icon_id": "13834325",
      "name": "赌博",
      "font_class": "f-gambling",
      "unicode": "e78d",
      "unicode_decimal": 59277
    },
    {
      "icon_id": "13834326",
      "name": "人员",
      "font_class": "f-personnel",
      "unicode": "e78e",
      "unicode_decimal": 59278
    },
    {
      "icon_id": "13834327",
      "name": "警情",
      "font_class": "f-Alarm",
      "unicode": "e78f",
      "unicode_decimal": 59279
    },
    {
      "icon_id": "13853187",
      "name": "数据库",
      "font_class": "f-database",
      "unicode": "e790",
      "unicode_decimal": 59280
    },
    {
      "icon_id": "13853188",
      "name": "商店",
      "font_class": "f-shop",
      "unicode": "e791",
      "unicode_decimal": 59281
    },
    {
      "icon_id": "13853189",
      "name": "通知",
      "font_class": "l-notice",
      "unicode": "e792",
      "unicode_decimal": 59282
    },
    {
      "icon_id": "13853190",
      "name": "核查",
      "font_class": "f-Check",
      "unicode": "e793",
      "unicode_decimal": 59283
    },
    {
      "icon_id": "13853192",
      "name": "-定位",
      "font_class": "f-location",
      "unicode": "e795",
      "unicode_decimal": 59285
    },
    {
      "icon_id": "13853193",
      "name": "场景",
      "font_class": "f-Scenes",
      "unicode": "e796",
      "unicode_decimal": 59286
    },
    {
      "icon_id": "13853194",
      "name": "档案",
      "font_class": "f-file1",
      "unicode": "e797",
      "unicode_decimal": 59287
    },
    {
      "icon_id": "13853195",
      "name": "下载",
      "font_class": "f-download",
      "unicode": "e798",
      "unicode_decimal": 59288
    },
    {
      "icon_id": "13853196",
      "name": "轨迹",
      "font_class": "f-Track",
      "unicode": "e799",
      "unicode_decimal": 59289
    },
    {
      "icon_id": "13853409",
      "name": "联络人",
      "font_class": "f-contacts",
      "unicode": "e794",
      "unicode_decimal": 59284
    },
    {
      "icon_id": "13867865",
      "name": "标签管理",
      "font_class": "f-tags",
      "unicode": "e79a",
      "unicode_decimal": 59290
    },
    {
      "icon_id": "13867866",
      "name": "标签",
      "font_class": "f-tag",
      "unicode": "e79b",
      "unicode_decimal": 59291
    },
    {
      "icon_id": "13899841",
      "name": "播放",
      "font_class": "f-play",
      "unicode": "e79c",
      "unicode_decimal": 59292
    },
    {
      "icon_id": "13899842",
      "name": "暂停",
      "font_class": "f-poweoff",
      "unicode": "e79d",
      "unicode_decimal": 59293
    },
    {
      "icon_id": "13899843",
      "name": "播放",
      "font_class": "l-play",
      "unicode": "e79e",
      "unicode_decimal": 59294
    },
    {
      "icon_id": "13899844",
      "name": "暂停",
      "font_class": "l-poweoff",
      "unicode": "e79f",
      "unicode_decimal": 59295
    },
    {
      "icon_id": "13899845",
      "name": "压缩包",
      "font_class": "f-zip",
      "unicode": "e7a0",
      "unicode_decimal": 59296
    },
    {
      "icon_id": "13899846",
      "name": "压缩包",
      "font_class": "l-zip",
      "unicode": "e7a1",
      "unicode_decimal": 59297
    },
    {
      "icon_id": "14104904",
      "name": "锁",
      "font_class": "f-lock",
      "unicode": "e7a2",
      "unicode_decimal": 59298
    },
    {
      "icon_id": "14104905",
      "name": "开锁",
      "font_class": "f-unlock",
      "unicode": "e7a3",
      "unicode_decimal": 59299
    },
    {
      "icon_id": "14104974",
      "name": "时间",
      "font_class": "l-time",
      "unicode": "e7a4",
      "unicode_decimal": 59300
    },
    {
      "icon_id": "14106319",
      "name": "线索查询",
      "font_class": "f-ClueQ",
      "unicode": "e7a5",
      "unicode_decimal": 59301
    },
    {
      "icon_id": "14106348",
      "name": "线索发件",
      "font_class": "f-ClueS",
      "unicode": "e7a6",
      "unicode_decimal": 59302
    },
    {
      "icon_id": "14106349",
      "name": "线索收件",
      "font_class": "f-ClueR",
      "unicode": "e7a7",
      "unicode_decimal": 59303
    },
    {
      "icon_id": "14106889",
      "name": "信息查询",
      "font_class": "f-InfoQ",
      "unicode": "e7a8",
      "unicode_decimal": 59304
    },
    {
      "icon_id": "14106890",
      "name": "待报信息",
      "font_class": "f-WaitI",
      "unicode": "e7a9",
      "unicode_decimal": 59305
    },
    {
      "icon_id": "14108351",
      "name": "线索研判",
      "font_class": "f-CluesR",
      "unicode": "e77d",
      "unicode_decimal": 59261
    },
    {
      "icon_id": "14108352",
      "name": "通知通报查询",
      "font_class": "f-NoticeQ",
      "unicode": "e7aa",
      "unicode_decimal": 59306
    },
    {
      "icon_id": "14826632",
      "name": "归并",
      "font_class": "l-Merge",
      "unicode": "e7ab",
      "unicode_decimal": 59307
    },
    {
      "icon_id": "15001109",
      "name": "紧急",
      "font_class": "l-urgent",
      "unicode": "e7ac",
      "unicode_decimal": 59308
    },
    {
      "icon_id": "15001110",
      "name": "紧急",
      "font_class": "f-urgent",
      "unicode": "e7ad",
      "unicode_decimal": 59309
    },
    {
      "icon_id": "15371815",
      "name": "手机",
      "font_class": "l-mobile",
      "unicode": "e7af",
      "unicode_decimal": 59311
    },
    {
      "icon_id": "15371960",
      "name": "车辆",
      "font_class": "l-car",
      "unicode": "e7ae",
      "unicode_decimal": 59310
    },
    {
      "icon_id": "15375991",
      "name": "群组",
      "font_class": "l-team",
      "unicode": "e7b1",
      "unicode_decimal": 59313
    },
    {
      "icon_id": "15376373",
      "name": "更多",
      "font_class": "f-more",
      "unicode": "e7b2",
      "unicode_decimal": 59314
    },
    {
      "icon_id": "15376374",
      "name": "更多",
      "font_class": "l-more",
      "unicode": "e7b3",
      "unicode_decimal": 59315
    },
    {
      "icon_id": "15493667",
      "name": "上传",
      "font_class": "l-upload",
      "unicode": "e7b4",
      "unicode_decimal": 59316
    },
    {
      "icon_id": "15493679",
      "name": "上传",
      "font_class": "f-upload",
      "unicode": "e7b5",
      "unicode_decimal": 59317
    },
    {
      "icon_id": "15493757",
      "name": "导入",
      "font_class": "daoru",
      "unicode": "e7b6",
      "unicode_decimal": 59318
    },
    {
      "icon_id": "15493805",
      "name": "导出",
      "font_class": "f-export",
      "unicode": "e7b7",
      "unicode_decimal": 59319
    },
    {
      "icon_id": "15674933",
      "name": "人员",
      "font_class": "l-personnel",
      "unicode": "e7b0",
      "unicode_decimal": 59312
    },
    {
      "icon_id": "15809294",
      "name": "分享",
      "font_class": "f-share",
      "unicode": "e7cb",
      "unicode_decimal": 59339
    },
    {
      "icon_id": "15809295",
      "name": "相交",
      "font_class": "l-intersect",
      "unicode": "e7cc",
      "unicode_decimal": 59340
    },
    {
      "icon_id": "15888340",
      "name": "往后",
      "font_class": "f-backward",
      "unicode": "e7cd",
      "unicode_decimal": 59341
    },
    {
      "icon_id": "15888341",
      "name": "快退",
      "font_class": "f-Fbackward",
      "unicode": "e7ce",
      "unicode_decimal": 59342
    },
    {
      "icon_id": "15888342",
      "name": "前进",
      "font_class": "f-forward",
      "unicode": "e7cf",
      "unicode_decimal": 59343
    },
    {
      "icon_id": "15888343",
      "name": "快进",
      "font_class": "f-Fforward",
      "unicode": "e7d0",
      "unicode_decimal": 59344
    },
    {
      "icon_id": "15888344",
      "name": "f-Cdown-下三角",
      "font_class": "f-Cdown",
      "unicode": "e7d1",
      "unicode_decimal": 59345
    },
    {
      "icon_id": "15888345",
      "name": "右三角",
      "font_class": "f-Cright",
      "unicode": "e7d2",
      "unicode_decimal": 59346
    },
    {
      "icon_id": "15888346",
      "name": "上三角",
      "font_class": "f-Cup",
      "unicode": "e7d3",
      "unicode_decimal": 59347
    },
    {
      "icon_id": "15888347",
      "name": "左三角",
      "font_class": "f-Cleft",
      "unicode": "e7d4",
      "unicode_decimal": 59348
    },
    {
      "icon_id": "16067764",
      "name": "闸机",
      "font_class": "f-Turnstile",
      "unicode": "e7d6",
      "unicode_decimal": 59350
    },
    {
      "icon_id": "16067765",
      "name": "应用",
      "font_class": "f-Appstore",
      "unicode": "e7d7",
      "unicode_decimal": 59351
    },
    {
      "icon_id": "16067766",
      "name": "地球",
      "font_class": "f-earth",
      "unicode": "e7d8",
      "unicode_decimal": 59352
    },
    {
      "icon_id": "16067767",
      "name": "中国",
      "font_class": "f-China",
      "unicode": "e7d9",
      "unicode_decimal": 59353
    },
    {
      "icon_id": "16264928",
      "name": "文件夹",
      "font_class": "f-folder",
      "unicode": "e7e8",
      "unicode_decimal": 59368
    },
    {
      "icon_id": "16514898",
      "name": "文件蓝色",
      "font_class": "f-blue",
      "unicode": "e7ec",
      "unicode_decimal": 59372
    },
    {
      "icon_id": "16634153",
      "name": "断开链接",
      "font_class": "l-disconnect",
      "unicode": "e7f2",
      "unicode_decimal": 59378
    },
    {
      "icon_id": "16641924",
      "name": "布控",
      "font_class": "l-aimsmubiao",
      "unicode": "e7f4",
      "unicode_decimal": 59380
    },
    {
      "icon_id": "16642490",
      "name": "轨迹",
      "font_class": "l-track",
      "unicode": "e7f5",
      "unicode_decimal": 59381
    },
    {
      "icon_id": "16871646",
      "name": "首页",
      "font_class": "f-homee",
      "unicode": "e7ff",
      "unicode_decimal": 59391
    },
    {
      "icon_id": "16871647",
      "name": "首页",
      "font_class": "l-Homee",
      "unicode": "e800",
      "unicode_decimal": 59392
    },
    {
      "icon_id": "16975690",
      "name": "手册",
      "font_class": "l-journal",
      "unicode": "e801",
      "unicode_decimal": 59393
    },
    {
      "icon_id": "17173416",
      "name": "应用",
      "font_class": "l-Appstore",
      "unicode": "e802",
      "unicode_decimal": 59394
    },
    {
      "icon_id": "17254003",
      "name": "人员轨迹",
      "font_class": "l-ptrack",
      "unicode": "e88c",
      "unicode_decimal": 59532
    },
    {
      "icon_id": "17254189",
      "name": "同意",
      "font_class": "l-agree",
      "unicode": "e88e",
      "unicode_decimal": 59534
    },
    {
      "icon_id": "17254421",
      "name": "退回",
      "font_class": "l-back",
      "unicode": "e88f",
      "unicode_decimal": 59535
    },
    {
      "icon_id": "17282354",
      "name": "场景",
      "font_class": "l-scense",
      "unicode": "e891",
      "unicode_decimal": 59537
    },
    {
      "icon_id": "17282355",
      "name": "场景",
      "font_class": "f-scense",
      "unicode": "e892",
      "unicode_decimal": 59538
    },
    {
      "icon_id": "17282356",
      "name": "审批",
      "font_class": "f-review",
      "unicode": "e893",
      "unicode_decimal": 59539
    },
    {
      "icon_id": "17371838",
      "name": "信",
      "font_class": "l-letterr",
      "unicode": "e8a5",
      "unicode_decimal": 59557
    },
    {
      "icon_id": "17371839",
      "name": "突出",
      "font_class": "l-outdent",
      "unicode": "e8a6",
      "unicode_decimal": 59558
    },
    {
      "icon_id": "17371840",
      "name": "缩进",
      "font_class": "l-indent",
      "unicode": "e8a7",
      "unicode_decimal": 59559
    },
    {
      "icon_id": "17371841",
      "name": "统计",
      "font_class": "l-statistics",
      "unicode": "e8a8",
      "unicode_decimal": 59560
    },
    {
      "icon_id": "17371842",
      "name": "视图",
      "font_class": "l-view",
      "unicode": "e8a9",
      "unicode_decimal": 59561
    },
    {
      "icon_id": "17371843",
      "name": "预警",
      "font_class": "l-Earlywarning",
      "unicode": "e8aa",
      "unicode_decimal": 59562
    },
    {
      "icon_id": "17371844",
      "name": "信息查询",
      "font_class": "l-InfoQ",
      "unicode": "e8ab",
      "unicode_decimal": 59563
    },
    {
      "icon_id": "17371883",
      "name": "模型",
      "font_class": "l-model",
      "unicode": "e8ac",
      "unicode_decimal": 59564
    },
    {
      "icon_id": "17371884",
      "name": "模型",
      "font_class": "f-model",
      "unicode": "e8ad",
      "unicode_decimal": 59565
    },
    {
      "icon_id": "17399960",
      "name": "返回",
      "font_class": "f-return",
      "unicode": "e8ae",
      "unicode_decimal": 59566
    },
    {
      "icon_id": "17399961",
      "name": "返回",
      "font_class": "l-return",
      "unicode": "e8af",
      "unicode_decimal": 59567
    },
    {
      "icon_id": "17399962",
      "name": "剪刀",
      "font_class": "l-scissors",
      "unicode": "e8b0",
      "unicode_decimal": 59568
    },
    {
      "icon_id": "17399963",
      "name": "筛选",
      "font_class": "l-filter",
      "unicode": "e8b1",
      "unicode_decimal": 59569
    },
    {
      "icon_id": "17688703",
      "name": "补充",
      "font_class": "l-supplement",
      "unicode": "e8cf",
      "unicode_decimal": 59599
    },
    {
      "icon_id": "17770938",
      "name": "热度",
      "font_class": "l-fire",
      "unicode": "e8d2",
      "unicode_decimal": 59602
    },
    {
      "icon_id": "17770939",
      "name": "热度",
      "font_class": "f-fire",
      "unicode": "e8d3",
      "unicode_decimal": 59603
    },
    {
      "icon_id": "17803743",
      "name": "旗帜",
      "font_class": "l-flag",
      "unicode": "e8d4",
      "unicode_decimal": 59604
    },
    {
      "icon_id": "17803744",
      "name": "撰写",
      "font_class": "l-write",
      "unicode": "e8d5",
      "unicode_decimal": 59605
    },
    {
      "icon_id": "17803745",
      "name": "值班",
      "font_class": "l-Onduty",
      "unicode": "e8d6",
      "unicode_decimal": 59606
    },
    {
      "icon_id": "17803746",
      "name": "电话",
      "font_class": "f-phone",
      "unicode": "e8d7",
      "unicode_decimal": 59607
    },
    {
      "icon_id": "17803747",
      "name": "手机",
      "font_class": "f-mobile",
      "unicode": "e8d8",
      "unicode_decimal": 59608
    },
    {
      "icon_id": "17803748",
      "name": "线索管理",
      "font_class": "l-clue",
      "unicode": "e8d9",
      "unicode_decimal": 59609
    },
    {
      "icon_id": "17803749",
      "name": "汇编",
      "font_class": "l-compile",
      "unicode": "e8da",
      "unicode_decimal": 59610
    },
    {
      "icon_id": "17803750",
      "name": "电话",
      "font_class": "l-phone",
      "unicode": "e8db",
      "unicode_decimal": 59611
    },
    {
      "icon_id": "17803751",
      "name": "在线",
      "font_class": "l-Online",
      "unicode": "e8dc",
      "unicode_decimal": 59612
    },
    {
      "icon_id": "17803752",
      "name": "重点人员",
      "font_class": "l-Keypersonnel",
      "unicode": "e8dd",
      "unicode_decimal": 59613
    },
    {
      "icon_id": "17905247",
      "name": "QQ",
      "font_class": "f-QQ",
      "unicode": "e8e5",
      "unicode_decimal": 59621
    },
    {
      "icon_id": "17905248",
      "name": "微信",
      "font_class": "f-WeChat",
      "unicode": "e8e6",
      "unicode_decimal": 59622
    },
    {
      "icon_id": "17905249",
      "name": "微信",
      "font_class": "l-WeChat",
      "unicode": "e8e7",
      "unicode_decimal": 59623
    },
    {
      "icon_id": "17905306",
      "name": "QQ",
      "font_class": "l-QQ",
      "unicode": "e8e8",
      "unicode_decimal": 59624
    },
    {
      "icon_id": "18066921",
      "name": "全屏",
      "font_class": "l-fullscreen",
      "unicode": "e8f8",
      "unicode_decimal": 59640
    },
    {
      "icon_id": "18066922",
      "name": "缩屏",
      "font_class": "l-reducescreen",
      "unicode": "e8f9",
      "unicode_decimal": 59641
    },
    {
      "icon_id": "18257872",
      "name": "换肤",
      "font_class": "f-skin",
      "unicode": "e906",
      "unicode_decimal": 59654
    },
    {
      "icon_id": "18258066",
      "name": "联络人",
      "font_class": "l-contacts",
      "unicode": "e907",
      "unicode_decimal": 59655
    },
    {
      "icon_id": "18260851",
      "name": "分享",
      "font_class": "l-share",
      "unicode": "e908",
      "unicode_decimal": 59656
    },
    {
      "icon_id": "18298693",
      "name": "警情",
      "font_class": "l-Policesituation",
      "unicode": "e90f",
      "unicode_decimal": 59663
    },
    {
      "icon_id": "18299095",
      "name": "绘制",
      "font_class": "l-draw",
      "unicode": "e911",
      "unicode_decimal": 59665
    },
    {
      "icon_id": "18299621",
      "name": "多边形",
      "font_class": "l-polygon",
      "unicode": "e912",
      "unicode_decimal": 59666
    },
    {
      "icon_id": "18306049",
      "name": "圆形",
      "font_class": "l-circular",
      "unicode": "e913",
      "unicode_decimal": 59667
    },
    {
      "icon_id": "18306183",
      "name": "反馈",
      "font_class": "l-feedback",
      "unicode": "e914",
      "unicode_decimal": 59668
    },
    {
      "icon_id": "18327659",
      "name": "打叉",
      "font_class": "l-cross",
      "unicode": "e915",
      "unicode_decimal": 59669
    },
    {
      "icon_id": "18327702",
      "name": "打勾",
      "font_class": "l-tick",
      "unicode": "e916",
      "unicode_decimal": 59670
    },
    {
      "icon_id": "18342814",
      "name": "最新",
      "font_class": "l-new",
      "unicode": "e91a",
      "unicode_decimal": 59674
    },
    {
      "icon_id": "18343627",
      "name": "感叹号",
      "font_class": "l-exclamatory",
      "unicode": "e91b",
      "unicode_decimal": 59675
    },
    {
      "icon_id": "18333848",
      "name": "定位点背景3",
      "font_class": "f-background3",
      "unicode": "e918",
      "unicode_decimal": 59672
    },
    {
      "icon_id": "18333851",
      "name": "定位点2",
      "font_class": "f-Anchor2",
      "unicode": "e919",
      "unicode_decimal": 59673
    },
    {
      "icon_id": "18354718",
      "name": "转移",
      "font_class": "l-transfer",
      "unicode": "e91c",
      "unicode_decimal": 59676
    },
    {
      "icon_id": "18380001",
      "name": "汽车",
      "font_class": "f-automobile",
      "unicode": "e91d",
      "unicode_decimal": 59677
    },
    {
      "icon_id": "18380002",
      "name": "民航",
      "font_class": "f-CivilAviation",
      "unicode": "e91e",
      "unicode_decimal": 59678
    },
    {
      "icon_id": "18380003",
      "name": "银行",
      "font_class": "f-bank",
      "unicode": "e91f",
      "unicode_decimal": 59679
    },
    {
      "icon_id": "18380004",
      "name": "驾驶证",
      "font_class": "f-driverslicense",
      "unicode": "e920",
      "unicode_decimal": 59680
    },
    {
      "icon_id": "18380005",
      "name": "卡口",
      "font_class": "f-Bayonet",
      "unicode": "e921",
      "unicode_decimal": 59681
    },
    {
      "icon_id": "18380047",
      "name": "终点",
      "font_class": "f-End",
      "unicode": "e922",
      "unicode_decimal": 59682
    },
    {
      "icon_id": "18380048",
      "name": "出入境",
      "font_class": "f-Entryandexit",
      "unicode": "e923",
      "unicode_decimal": 59683
    },
    {
      "icon_id": "18380049",
      "name": "轮渡",
      "font_class": "f-ferry",
      "unicode": "e924",
      "unicode_decimal": 59684
    },
    {
      "icon_id": "18380050",
      "name": "网吧",
      "font_class": "f-InternetBar",
      "unicode": "e925",
      "unicode_decimal": 59685
    },
    {
      "icon_id": "18380051",
      "name": "医院就诊",
      "font_class": "f-Hospitalvisits",
      "unicode": "e926",
      "unicode_decimal": 59686
    },
    {
      "icon_id": "18380133",
      "name": "手机",
      "font_class": "f-mobilephone",
      "unicode": "e927",
      "unicode_decimal": 59687
    },
    {
      "icon_id": "18380134",
      "name": "交管处罚",
      "font_class": "f-jgcf",
      "unicode": "e928",
      "unicode_decimal": 59688
    },
    {
      "icon_id": "18380135",
      "name": "物流快递",
      "font_class": "f-logistics",
      "unicode": "e929",
      "unicode_decimal": 59689
    },
    {
      "icon_id": "18380136",
      "name": "人员盘查",
      "font_class": "f-Personnelcheck",
      "unicode": "e92a",
      "unicode_decimal": 59690
    },
    {
      "icon_id": "18380137",
      "name": "人像照片",
      "font_class": "f-Portraitphoto",
      "unicode": "e92b",
      "unicode_decimal": 59691
    },
    {
      "icon_id": "18380138",
      "name": "治安业务办理",
      "font_class": "f-publicsecurity",
      "unicode": "e92c",
      "unicode_decimal": 59692
    },
    {
      "icon_id": "18380139",
      "name": "购物",
      "font_class": "f-shopping",
      "unicode": "e92d",
      "unicode_decimal": 59693
    },
    {
      "icon_id": "11842702",
      "name": "背审审核",
      "font_class": "f-beishenshenhe",
      "unicode": "e725",
      "unicode_decimal": 59173
    },
    {
      "icon_id": "18380140",
      "name": "出入所记录",
      "font_class": "f-Prisonrecords",
      "unicode": "e92e",
      "unicode_decimal": 59694
    },
    {
      "icon_id": "11842703",
      "name": "待办工作",
      "font_class": "f-daibangongzuo",
      "unicode": "e728",
      "unicode_decimal": 59176
    },
    {
      "icon_id": "18380141",
      "name": "起点",
      "font_class": "f-startingpoint",
      "unicode": "e92f",
      "unicode_decimal": 59695
    },
    {
      "icon_id": "11842704",
      "name": "快速申请",
      "font_class": "f-kuaisushenqing",
      "unicode": "e72b",
      "unicode_decimal": 59179
    },
    {
      "icon_id": "18380294",
      "name": "出租车",
      "font_class": "f-taxi",
      "unicode": "e930",
      "unicode_decimal": 59696
    },
    {
      "icon_id": "11842705",
      "name": "首页",
      "font_class": "f-home",
      "unicode": "e72c",
      "unicode_decimal": 59180
    },
    {
      "icon_id": "18380295",
      "name": "旅业",
      "font_class": "f-Tourism",
      "unicode": "e931",
      "unicode_decimal": 59697
    },
    {
      "icon_id": "11842706",
      "name": "背审查询",
      "font_class": "f-beishenchaxun",
      "unicode": "e72d",
      "unicode_decimal": 59181
    },
    {
      "icon_id": "18380296",
      "name": "wifi",
      "font_class": "f-Wifi",
      "unicode": "e932",
      "unicode_decimal": 59698
    },
    {
      "icon_id": "11842707",
      "name": "背审申请",
      "font_class": "f-apply",
      "unicode": "e72e",
      "unicode_decimal": 59182
    },
    {
      "icon_id": "18380297",
      "name": "虚拟身份",
      "font_class": "f-Virtualidentity",
      "unicode": "e933",
      "unicode_decimal": 59699
    },
    {
      "icon_id": "11842709",
      "name": "背审复核",
      "font_class": "f-through-",
      "unicode": "e72f",
      "unicode_decimal": 59183
    },
    {
      "icon_id": "18380298",
      "name": "火车",
      "font_class": "f-train",
      "unicode": "e934",
      "unicode_decimal": 59700
    },
    {
      "icon_id": "11842849",
      "name": "统计分析",
      "font_class": "f-tongjifenxi",
      "unicode": "e730",
      "unicode_decimal": 59184
    },
    {
      "icon_id": "18380299",
      "name": "机动车",
      "font_class": "f-Vehicle",
      "unicode": "e935",
      "unicode_decimal": 59701
    },
    {
      "icon_id": "11842884",
      "name": "通过",
      "font_class": "f-circle-check",
      "unicode": "e731",
      "unicode_decimal": 59185
    },
    {
      "icon_id": "18393788",
      "name": "防空圈",
      "font_class": "l-Airdefensecircle",
      "unicode": "e936",
      "unicode_decimal": 59702
    },
    {
      "icon_id": "11842889",
      "name": "不通过",
      "font_class": "f-circle-close",
      "unicode": "e732",
      "unicode_decimal": 59186
    },
    {
      "icon_id": "18393789",
      "name": "在逃",
      "font_class": "l-Atlarge",
      "unicode": "e937",
      "unicode_decimal": 59703
    },
    {
      "icon_id": "11842890",
      "name": "提示",
      "font_class": "f-circle-error",
      "unicode": "e733",
      "unicode_decimal": 59187
    },
    {
      "icon_id": "11842882",
      "name": "无效人员",
      "font_class": "f-invaliduser",
      "unicode": "e734",
      "unicode_decimal": 59188
    },
    {
      "icon_id": "11842888",
      "name": "总人数",
      "font_class": "f-team",
      "unicode": "e735",
      "unicode_decimal": 59189
    },
    {
      "icon_id": "11842880",
      "name": "不通过数",
      "font_class": "f-fail",
      "unicode": "e736",
      "unicode_decimal": 59190
    },
    {
      "icon_id": "11842881",
      "name": "总数",
      "font_class": "f-file",
      "unicode": "e737",
      "unicode_decimal": 59191
    },
    {
      "icon_id": "11842886",
      "name": "通过数",
      "font_class": "f-through",
      "unicode": "e738",
      "unicode_decimal": 59192
    },
    {
      "icon_id": "11842883",
      "name": "列表",
      "font_class": "f-list",
      "unicode": "e739",
      "unicode_decimal": 59193
    }
  ]
}
